CHANGES.rst
MANIFEST.in
README.rst
setup.cfg
setup.py
collective/__init__.py
collective/__init__.pyc
collective.classifieds.egg-info/PKG-INFO
collective.classifieds.egg-info/SOURCES.txt
collective.classifieds.egg-info/dependency_links.txt
collective.classifieds.egg-info/entry_points.txt
collective.classifieds.egg-info/namespace_packages.txt
collective.classifieds.egg-info/not-zip-safe
collective.classifieds.egg-info/requires.txt
collective.classifieds.egg-info/top_level.txt
collective/classifieds/__init__.py
collective/classifieds/config.py
collective/classifieds/configure.zcml
collective/classifieds/profiles.zcml
collective/classifieds/refresh.txt
collective/classifieds/setuphandlers.py
collective/classifieds/version.txt
collective/classifieds/browser/__init__.py
collective/classifieds/browser/all_classifieds_view.py
collective/classifieds/browser/browser.zcml
collective/classifieds/browser/classified_view.py
collective/classifieds/browser/classifieds_by_author_view.py
collective/classifieds/browser/classifiedscategory_view.py
collective/classifieds/browser/list_view.py
collective/classifieds/browser/search.py
collective/classifieds/browser/css/classifieds.css
collective/classifieds/browser/images/Classified.gif
collective/classifieds/browser/images/Classifieds.gif
collective/classifieds/browser/images/ClassifiedsCategory.gif
collective/classifieds/browser/images/no_photo.jpg
collective/classifieds/browser/templates/all_classifieds_view.pt
collective/classifieds/browser/templates/classified_view.pt
collective/classifieds/browser/templates/classifieds_by_author_view.pt
collective/classifieds/browser/templates/classifiedscategory_view.pt
collective/classifieds/browser/templates/list_view.pt
collective/classifieds/content/Classified.py
collective/classifieds/content/Classifieds.py
collective/classifieds/content/ClassifiedsCategory.py
collective/classifieds/content/OrderedClassifieds.py
collective/classifieds/content/OrderedClassifiedsCategory.py
collective/classifieds/content/Validators.py
collective/classifieds/content/__init__.py
collective/classifieds/content/interfaces.py
collective/classifieds/locales/collective.classifieds.pot
collective/classifieds/locales/manual.pot
collective/classifieds/locales/plone.pot
collective/classifieds/locales/cs/LC_MESSAGES/collective.classifieds.mo
