Metadata-Version: 1.1
Name: collective.classifieds
Version: 1.7
Summary: Add classifieds to your Plone intranet or website.
Home-page: http://www.plone.org/products/classifieds
Author: Four Digits (ralph@fourdigits.nl)
Author-email: ralph@fourdigits.nl
License: GPL
Keywords: classifieds sales intranet
Platform: UNKNOWN
Classifier: Framework :: Plone
Classifier: Framework :: Plone :: 4.0
Classifier: Framework :: Plone :: 4.1
Classifier: Framework :: Plone :: 4.2
Classifier: Framework :: Plone :: 4.3
Classifier: Programming Language :: Python
Classifier: Topic :: Software Development :: Libraries :: Python Modules
